{
    "pages": [
        "ComforterBrush-Regular.png"
    ],
    "chars": [
        {
            "id": 71,
            "index": 11,
            "char": "G",
            "width": 47,
            "height": 77,
            "xoffset": -3,
            "yoffset": 13,
            "xadvance": 35,
            "chnl": 15,
            "x": 0,
            "y": 0,
            "page": 0
        },
        {
            "id": 102,
            "index": 36,
            "char": "f",
            "width": 32,
            "height": 73,
            "xoffset": -3,
            "yoffset": 20,
            "xadvance": 20,
            "chnl": 15,
            "x": 48,
            "y": 0,
            "page": 0
        },
        {
            "id": 74,
            "index": 14,
            "char": "J",
            "width": 40,
            "height": 72,
            "xoffset": -2,
            "yoffset": 18,
            "xadvance": 28,
            "chnl": 15,
            "x": 81,
            "y": 0,
            "page": 0
        },
        {
            "id": 81,
            "index": 21,
            "char": "Q",
            "width": 71,
            "height": 69,
            "xoffset": -2,
            "yoffset": 16,
            "xadvance": 49,
            "chnl": 15,
            "x": 122,
            "y": 0,
            "page": 0
        },
        {
            "id": 89,
            "index": 29,
            "char": "Y",
            "width": 61,
            "height": 70,
            "xoffset": -2,
            "yoffset": 12,
            "xadvance": 56,
            "chnl": 15,
            "x": 194,
            "y": 0,
            "page": 0
        },
        {
            "id": 79,
            "index": 19,
            "char": "O",
            "width": 69,
            "height": 57,
            "xoffset": -1,
            "yoffset": 17,
            "xadvance": 66,
            "chnl": 15,
            "x": 122,
            "y": 71,
            "page": 0
        },
        {
            "id": 112,
            "index": 46,
            "char": "p",
            "width": 35,
            "height": 69,
            "xoffset": -3,
            "yoffset": 28,
            "xadvance": 25,
            "chnl": 15,
            "x": 81,
            "y": 73,
            "page": 0
        },
        {
            "id": 38,
            "index": 868,
            "char": "&",
            "width": 44,
            "height": 68,
            "xoffset": 4,
            "yoffset": 9,
            "xadvance": 47,
            "chnl": 15,
            "x": 192,
            "y": 71,
            "page": 0
        },
        {
            "id": 87,
            "index": 27,
            "char": "W",
            "width": 68,
            "height": 58,
            "xoffset": -1,
            "yoffset": 13,
            "xadvance": 54,
            "chnl": 15,
            "x": 117,
            "y": 129,
            "page": 0
        },
        {
            "id": 80,
            "index": 20,
            "char": "P",
            "width": 46,
            "height": 67,
            "xoffset": -3,
            "yoffset": 12,
            "xadvance": 35,
            "chnl": 15,
            "x": 0,
            "y": 188,
            "page": 0
        },
        {
            "id": 84,
            "index": 24,
            "char": "T",
            "width": 66,
            "height": 61,
            "xoffset": -3,
            "yoffset": 13,
            "xadvance": 35,
            "chnl": 15,
            "x": 47,
            "y": 143,
            "page": 0
        },
        {
            "id": 66,
            "index": 6,
            "char": "B",
            "width": 48,
            "height": 63,
            "xoffset": -1,
            "yoffset": 11,
            "xadvance": 40,
            "chnl": 15,
            "x": 0,
            "y": 78,
            "page": 0
        },
        {
            "id": 72,
            "index": 12,
            "char": "H",
            "width": 48,
            "height": 63,
            "xoffset": -9,
            "yoffset": 10,
            "xadvance": 39,
            "chnl": 15,
            "x": 114,
            "y": 188,
            "page": 0
        },
        {
            "id": 75,
            "index": 15,
            "char": "K",
            "width": 35,
            "height": 63,
            "xoffset": 1,
            "yoffset": 10,
            "xadvance": 35,
            "chnl": 15,
            "x": 163,
            "y": 188,
            "page": 0
        },
        {
            "id": 65,
            "index": 5,
            "char": "A",
            "width": 46,
            "height": 62,
            "xoffset": -8,
            "yoffset": 10,
            "xadvance": 33,
            "chnl": 15,
            "x": 199,
            "y": 140,
            "page": 0
        },
        {
            "id": 67,
            "index": 7,
            "char": "C",
            "width": 62,
            "height": 60,
            "xoffset": 0,
            "yoffset": 14,
            "xadvance": 56,
            "chnl": 15,
            "x": 237,
            "y": 71,
            "page": 0
        },
        {
            "id": 70,
            "index": 10,
            "char": "F",
            "width": 54,
            "height": 62,
            "xoffset": -2,
            "yoffset": 7,
            "xadvance": 38,
            "chnl": 15,
            "x": 256,
            "y": 0,
            "page": 0
        },
        {
            "id": 76,
            "index": 16,
            "char": "L",
            "width": 52,
            "height": 61,
            "xoffset": -10,
            "yoffset": 14,
            "xadvance": 27,
            "chnl": 15,
            "x": 246,
            "y": 132,
            "page": 0
        },
        {
            "id": 106,
            "index": 40,
            "char": "j",
            "width": 28,
            "height": 61,
            "xoffset": -12,
            "yoffset": 32,
            "xadvance": 11,
            "chnl": 15,
            "x": 246,
            "y": 194,
            "page": 0
        },
        {
            "id": 121,
            "index": 55,
            "char": "y",
            "width": 28,
            "height": 61,
            "xoffset": -3,
            "yoffset": 35,
            "xadvance": 19,
            "chnl": 15,
            "x": 275,
            "y": 194,
            "page": 0
        },
        {
            "id": 68,
            "index": 8,
            "char": "D",
            "width": 49,
            "height": 60,
            "xoffset": -2,
            "yoffset": 14,
            "xadvance": 44,
            "chnl": 15,
            "x": 299,
            "y": 132,
            "page": 0
        },
        {
            "id": 69,
            "index": 9,
            "char": "E",
            "width": 47,
            "height": 60,
            "xoffset": -3,
            "yoffset": 13,
            "xadvance": 34,
            "chnl": 15,
            "x": 304,
            "y": 193,
            "page": 0
        },
        {
            "id": 88,
            "index": 28,
            "char": "X",
            "width": 57,
            "height": 60,
            "xoffset": -9,
            "yoffset": 14,
            "xadvance": 35,
            "chnl": 15,
            "x": 300,
            "y": 63,
            "page": 0
        },
        {
            "id": 73,
            "index": 13,
            "char": "I",
            "width": 50,
            "height": 59,
            "xoffset": -13,
            "yoffset": 15,
            "xadvance": 25,
            "chnl": 15,
            "x": 311,
            "y": 0,
            "page": 0
        },
        {
            "id": 82,
            "index": 22,
            "char": "R",
            "width": 41,
            "height": 59,
            "xoffset": -1,
            "yoffset": 12,
            "xadvance": 33,
            "chnl": 15,
            "x": 349,
            "y": 124,
            "page": 0
        },
        {
            "id": 83,
            "index": 23,
            "char": "S",
            "width": 51,
            "height": 58,
            "xoffset": -2,
            "yoffset": 11,
            "xadvance": 42,
            "chnl": 15,
            "x": 358,
            "y": 60,
            "page": 0
        },
        {
            "id": 90,
            "index": 30,
            "char": "Z",
            "width": 51,
            "height": 58,
            "xoffset": -2,
            "yoffset": 17,
            "xadvance": 42,
            "chnl": 15,
            "x": 362,
            "y": 0,
            "page": 0
        },
        {
            "id": 100,
            "index": 34,
            "char": "d",
            "width": 35,
            "height": 57,
            "xoffset": -2,
            "yoffset": 15,
            "xadvance": 26,
            "chnl": 15,
            "x": 352,
            "y": 184,
            "page": 0
        },
        {
            "id": 85,
            "index": 25,
            "char": "U",
            "width": 51,
            "height": 55,
            "xoffset": -1,
            "yoffset": 13,
            "xadvance": 44,
            "chnl": 15,
            "x": 388,
            "y": 184,
            "page": 0
        },
        {
            "id": 103,
            "index": 37,
            "char": "g",
            "width": 28,
            "height": 55,
            "xoffset": -1,
            "yoffset": 38,
            "xadvance": 22,
            "chnl": 15,
            "x": 49,
            "y": 74,
            "page": 0
        },
        {
            "id": 104,
            "index": 38,
            "char": "h",
            "width": 24,
            "height": 55,
            "xoffset": 2,
            "yoffset": 14,
            "xadvance": 19,
            "chnl": 15,
            "x": 391,
            "y": 119,
            "page": 0
        },
        {
            "id": 107,
            "index": 41,
            "char": "k",
            "width": 24,
            "height": 55,
            "xoffset": 0,
            "yoffset": 14,
            "xadvance": 18,
            "chnl": 15,
            "x": 410,
            "y": 59,
            "page": 0
        },
        {
            "id": 86,
            "index": 26,
            "char": "V",
            "width": 53,
            "height": 53,
            "xoffset": -2,
            "yoffset": 13,
            "xadvance": 41,
            "chnl": 15,
            "x": 414,
            "y": 0,
            "page": 0
        },
        {
            "id": 108,
            "index": 42,
            "char": "l",
            "width": 17,
            "height": 53,
            "xoffset": 1,
            "yoffset": 15,
            "xadvance": 13,
            "chnl": 15,
            "x": 199,
            "y": 203,
            "page": 0
        },
        {
            "id": 116,
            "index": 50,
            "char": "t",
            "width": 47,
            "height": 53,
            "xoffset": -10,
            "yoffset": 14,
            "xadvance": 12,
            "chnl": 15,
            "x": 416,
            "y": 115,
            "page": 0
        },
        {
            "id": 47,
            "index": 783,
            "char": "/",
            "width": 30,
            "height": 52,
            "xoffset": 2,
            "yoffset": 18,
            "xadvance": 27,
            "chnl": 15,
            "x": 435,
            "y": 54,
            "page": 0
        },
        {
            "id": 77,
            "index": 17,
            "char": "M",
            "width": 44,
            "height": 52,
            "xoffset": 2,
            "yoffset": 15,
            "xadvance": 43,
            "chnl": 15,
            "x": 468,
            "y": 0,
            "page": 0
        },
        {
            "id": 78,
            "index": 18,
            "char": "N",
            "width": 37,
            "height": 52,
            "xoffset": -1,
            "yoffset": 16,
            "xadvance": 30,
            "chnl": 15,
            "x": 468,
            "y": 53,
            "page": 0
        },
        {
            "id": 125,
            "index": 790,
            "char": "}",
            "width": 22,
            "height": 52,
            "xoffset": 3,
            "yoffset": 20,
            "xadvance": 24,
            "chnl": 15,
            "x": 217,
            "y": 203,
            "page": 0
        },
        {
            "id": 123,
            "index": 789,
            "char": "{",
            "width": 21,
            "height": 51,
            "xoffset": 4,
            "yoffset": 20,
            "xadvance": 26,
            "chnl": 15,
            "x": 47,
            "y": 205,
            "page": 0
        },
        {
            "id": 92,
            "index": 784,
            "char": "\\",
            "width": 26,
            "height": 50,
            "xoffset": 3,
            "yoffset": 22,
            "xadvance": 28,
            "chnl": 15,
            "x": 69,
            "y": 205,
            "page": 0
        },
        {
            "id": 91,
            "index": 791,
            "char": "[",
            "width": 23,
            "height": 49,
            "xoffset": 2,
            "yoffset": 22,
            "xadvance": 25,
            "chnl": 15,
            "x": 466,
            "y": 106,
            "page": 0
        },
        {
            "id": 93,
            "index": 792,
            "char": "]",
            "width": 23,
            "height": 49,
            "xoffset": 1,
            "yoffset": 22,
            "xadvance": 24,
            "chnl": 15,
            "x": 464,
            "y": 156,
            "page": 0
        },
        {
            "id": 36,
            "index": 818,
            "char": "$",
            "width": 23,
            "height": 48,
            "xoffset": 5,
            "yoffset": 25,
            "xadvance": 28,
            "chnl": 15,
            "x": 440,
            "y": 169,
            "page": 0
        },
        {
            "id": 98,
            "index": 32,
            "char": "b",
            "width": 24,
            "height": 48,
            "xoffset": 0,
            "yoffset": 15,
            "xadvance": 22,
            "chnl": 15,
            "x": 488,
            "y": 156,
            "page": 0
        },
        {
            "id": 37,
            "index": 864,
            "char": "%",
            "width": 28,
            "height": 46,
            "xoffset": 2,
            "yoffset": 24,
            "xadvance": 27,
            "chnl": 15,
            "x": 464,
            "y": 206,
            "page": 0
        },
        {
            "id": 64,
            "index": 867,
            "char": "@",
            "width": 46,
            "height": 43,
            "xoffset": 3,
            "yoffset": 22,
            "xadvance": 50,
            "chnl": 15,
            "x": 0,
            "y": 142,
            "page": 0
        },
        {
            "id": 113,
            "index": 47,
            "char": "q",
            "width": 29,
            "height": 46,
            "xoffset": 0,
            "yoffset": 40,
            "xadvance": 25,
            "chnl": 15,
            "x": 0,
            "y": 256,
            "page": 0
        },
        {
            "id": 33,
            "index": 775,
            "char": "!",
            "width": 12,
            "height": 45,
            "xoffset": 5,
            "yoffset": 22,
            "xadvance": 18,
            "chnl": 15,
            "x": 186,
            "y": 140,
            "page": 0
        },
        {
            "id": 63,
            "index": 777,
            "char": "?",
            "width": 21,
            "height": 45,
            "xoffset": 3,
            "yoffset": 22,
            "xadvance": 22,
            "chnl": 15,
            "x": 490,
            "y": 106,
            "page": 0
        },
        {
            "id": 124,
            "index": 877,
            "char": "|",
            "width": 9,
            "height": 45,
            "xoffset": 4,
            "yoffset": 22,
            "xadvance": 16,
            "chnl": 15,
            "x": 30,
            "y": 256,
            "page": 0
        },
        {
            "id": 35,
            "index": 782,
            "char": "#",
            "width": 39,
            "height": 43,
            "xoffset": 3,
            "yoffset": 21,
            "xadvance": 41,
            "chnl": 15,
            "x": 388,
            "y": 240,
            "page": 0
        },
        {
            "id": 40,
            "index": 787,
            "char": "(",
            "width": 21,
            "height": 43,
            "xoffset": 3,
            "yoffset": 27,
            "xadvance": 17,
            "chnl": 15,
            "x": 440,
            "y": 218,
            "page": 0
        },
        {
            "id": 41,
            "index": 788,
            "char": ")",
            "width": 21,
            "height": 43,
            "xoffset": -3,
            "yoffset": 27,
            "xadvance": 17,
            "chnl": 15,
            "x": 352,
            "y": 242,
            "page": 0
        },
        {
            "id": 49,
            "index": 743,
            "char": "1",
            "width": 14,
            "height": 41,
            "xoffset": 2,
            "yoffset": 28,
            "xadvance": 12,
            "chnl": 15,
            "x": 96,
            "y": 205,
            "page": 0
        },
        {
            "id": 52,
            "index": 746,
            "char": "4",
            "width": 30,
            "height": 41,
            "xoffset": -2,
            "yoffset": 28,
            "xadvance": 26,
            "chnl": 15,
            "x": 304,
            "y": 254,
            "page": 0
        },
        {
            "id": 53,
            "index": 747,
            "char": "5",
            "width": 29,
            "height": 41,
            "xoffset": -1,
            "yoffset": 29,
            "xadvance": 24,
            "chnl": 15,
            "x": 462,
            "y": 253,
            "page": 0
        },
        {
            "id": 119,
            "index": 53,
            "char": "w",
            "width": 41,
            "height": 25,
            "xoffset": 1,
            "yoffset": 39,
            "xadvance": 36,
            "chnl": 15,
            "x": 217,
            "y": 256,
            "page": 0
        },
        {
            "id": 50,
            "index": 744,
            "char": "2",
            "width": 31,
            "height": 40,
            "xoffset": -1,
            "yoffset": 29,
            "xadvance": 25,
            "chnl": 15,
            "x": 428,
            "y": 262,
            "page": 0
        },
        {
            "id": 54,
            "index": 748,
            "char": "6",
            "width": 27,
            "height": 40,
            "xoffset": 0,
            "yoffset": 28,
            "xadvance": 26,
            "chnl": 15,
            "x": 259,
            "y": 256,
            "page": 0
        },
        {
            "id": 55,
            "index": 749,
            "char": "7",
            "width": 26,
            "height": 40,
            "xoffset": 2,
            "yoffset": 29,
            "xadvance": 22,
            "chnl": 15,
            "x": 460,
            "y": 295,
            "page": 0
        },
        {
            "id": 56,
            "index": 750,
            "char": "8",
            "width": 28,
            "height": 40,
            "xoffset": 0,
            "yoffset": 27,
            "xadvance": 26,
            "chnl": 15,
            "x": 374,
            "y": 284,
            "page": 0
        },
        {
            "id": 57,
            "index": 751,
            "char": "9",
            "width": 24,
            "height": 40,
            "xoffset": 0,
            "yoffset": 28,
            "xadvance": 23,
            "chnl": 15,
            "x": 403,
            "y": 284,
            "page": 0
        },
        {
            "id": 95,
            "index": 799,
            "char": "_",
            "width": 40,
            "height": 6,
            "xoffset": -3,
            "yoffset": 63,
            "xadvance": 34,
            "chnl": 15,
            "x": 256,
            "y": 63,
            "page": 0
        },
        {
            "id": 51,
            "index": 745,
            "char": "3",
            "width": 27,
            "height": 39,
            "xoffset": 1,
            "yoffset": 29,
            "xadvance": 28,
            "chnl": 15,
            "x": 428,
            "y": 303,
            "page": 0
        },
        {
            "id": 120,
            "index": 54,
            "char": "x",
            "width": 32,
            "height": 39,
            "xoffset": -7,
            "yoffset": 33,
            "xadvance": 18,
            "chnl": 15,
            "x": 335,
            "y": 286,
            "page": 0
        },
        {
            "id": 48,
            "index": 742,
            "char": "0",
            "width": 28,
            "height": 38,
            "xoffset": 2,
            "yoffset": 28,
            "xadvance": 31,
            "chnl": 15,
            "x": 287,
            "y": 296,
            "page": 0
        },
        {
            "id": 110,
            "index": 44,
            "char": "n",
            "width": 29,
            "height": 37,
            "xoffset": -2,
            "yoffset": 34,
            "xadvance": 20,
            "chnl": 15,
            "x": 456,
            "y": 336,
            "page": 0
        },
        {
            "id": 109,
            "index": 43,
            "char": "m",
            "width": 32,
            "height": 36,
            "xoffset": -2,
            "yoffset": 35,
            "xadvance": 24,
            "chnl": 15,
            "x": 368,
            "y": 325,
            "page": 0
        },
        {
            "id": 122,
            "index": 56,
            "char": "z",
            "width": 27,
            "height": 34,
            "xoffset": 0,
            "yoffset": 33,
            "xadvance": 21,
            "chnl": 15,
            "x": 316,
            "y": 326,
            "page": 0
        },
        {
            "id": 59,
            "index": 773,
            "char": ";",
            "width": 13,
            "height": 33,
            "xoffset": 2,
            "yoffset": 41,
            "xadvance": 13,
            "chnl": 15,
            "x": 374,
            "y": 242,
            "page": 0
        },
        {
            "id": 99,
            "index": 33,
            "char": "c",
            "width": 30,
            "height": 33,
            "xoffset": -1,
            "yoffset": 35,
            "xadvance": 27,
            "chnl": 15,
            "x": 401,
            "y": 343,
            "page": 0
        },
        {
            "id": 111,
            "index": 45,
            "char": "o",
            "width": 33,
            "height": 30,
            "xoffset": 0,
            "yoffset": 34,
            "xadvance": 25,
            "chnl": 15,
            "x": 432,
            "y": 374,
            "page": 0
        },
        {
            "id": 117,
            "index": 51,
            "char": "u",
            "width": 27,
            "height": 33,
            "xoffset": -2,
            "yoffset": 33,
            "xadvance": 19,
            "chnl": 15,
            "x": 466,
            "y": 374,
            "page": 0
        },
        {
            "id": 101,
            "index": 35,
            "char": "e",
            "width": 20,
            "height": 31,
            "xoffset": 1,
            "yoffset": 34,
            "xadvance": 14,
            "chnl": 15,
            "x": 492,
            "y": 253,
            "page": 0
        },
        {
            "id": 114,
            "index": 48,
            "char": "r",
            "width": 25,
            "height": 31,
            "xoffset": 0,
            "yoffset": 31,
            "xadvance": 18,
            "chnl": 15,
            "x": 487,
            "y": 295,
            "page": 0
        },
        {
            "id": 43,
            "index": 840,
            "char": "+",
            "width": 26,
            "height": 30,
            "xoffset": 2,
            "yoffset": 32,
            "xadvance": 21,
            "chnl": 15,
            "x": 486,
            "y": 336,
            "page": 0
        },
        {
            "id": 115,
            "index": 49,
            "char": "s",
            "width": 23,
            "height": 29,
            "xoffset": -1,
            "yoffset": 34,
            "xadvance": 17,
            "chnl": 15,
            "x": 344,
            "y": 326,
            "page": 0
        },
        {
            "id": 105,
            "index": 39,
            "char": "i",
            "width": 16,
            "height": 28,
            "xoffset": 0,
            "yoffset": 36,
            "xadvance": 9,
            "chnl": 15,
            "x": 335,
            "y": 254,
            "page": 0
        },
        {
            "id": 118,
            "index": 52,
            "char": "v",
            "width": 25,
            "height": 28,
            "xoffset": -1,
            "yoffset": 37,
            "xadvance": 19,
            "chnl": 15,
            "x": 0,
            "y": 408,
            "page": 0
        },
        {
            "id": 58,
            "index": 772,
            "char": ":",
            "width": 10,
            "height": 27,
            "xoffset": 5,
            "yoffset": 41,
            "xadvance": 13,
            "chnl": 15,
            "x": 316,
            "y": 296,
            "page": 0
        },
        {
            "id": 97,
            "index": 31,
            "char": "a",
            "width": 25,
            "height": 26,
            "xoffset": 0,
            "yoffset": 37,
            "xadvance": 20,
            "chnl": 15,
            "x": 0,
            "y": 377,
            "page": 0
        },
        {
            "id": 60,
            "index": 847,
            "char": "<",
            "width": 19,
            "height": 25,
            "xoffset": 4,
            "yoffset": 33,
            "xadvance": 24,
            "chnl": 15,
            "x": 493,
            "y": 205,
            "page": 0
        },
        {
            "id": 62,
            "index": 846,
            "char": ">",
            "width": 19,
            "height": 24,
            "xoffset": 4,
            "yoffset": 34,
            "xadvance": 24,
            "chnl": 15,
            "x": 432,
            "y": 343,
            "page": 0
        },
        {
            "id": 61,
            "index": 844,
            "char": "=",
            "width": 23,
            "height": 20,
            "xoffset": 5,
            "yoffset": 39,
            "xadvance": 27,
            "chnl": 15,
            "x": 344,
            "y": 356,
            "page": 0
        },
        {
            "id": 42,
            "index": 781,
            "char": "*",
            "width": 19,
            "height": 21,
            "xoffset": 3,
            "yoffset": 14,
            "xadvance": 21,
            "chnl": 15,
            "x": 493,
            "y": 231,
            "page": 0
        },
        {
            "id": 45,
            "index": 793,
            "char": "-",
            "width": 19,
            "height": 8,
            "xoffset": 5,
            "yoffset": 44,
            "xadvance": 23,
            "chnl": 15,
            "x": 391,
            "y": 175,
            "page": 0
        },
        {
            "id": 94,
            "index": 854,
            "char": "^",
            "width": 18,
            "height": 15,
            "xoffset": 3,
            "yoffset": 22,
            "xadvance": 24,
            "chnl": 15,
            "x": 494,
            "y": 367,
            "page": 0
        },
        {
            "id": 126,
            "index": 852,
            "char": "~",
            "width": 18,
            "height": 8,
            "xoffset": 1,
            "yoffset": 25,
            "xadvance": 19,
            "chnl": 15,
            "x": 487,
            "y": 327,
            "page": 0
        },
        {
            "id": 44,
            "index": 771,
            "char": ",",
            "width": 12,
            "height": 16,
            "xoffset": -3,
            "yoffset": 58,
            "xadvance": 10,
            "chnl": 15,
            "x": 401,
            "y": 325,
            "page": 0
        },
        {
            "id": 34,
            "index": 810,
            "char": "\"",
            "width": 15,
            "height": 12,
            "xoffset": 1,
            "yoffset": 26,
            "xadvance": 14,
            "chnl": 15,
            "x": 49,
            "y": 130,
            "page": 0
        },
        {
            "id": 96,
            "index": 87,
            "char": "`",
            "width": 13,
            "height": 10,
            "xoffset": -2,
            "yoffset": 27,
            "xadvance": 9,
            "chnl": 15,
            "x": 414,
            "y": 325,
            "page": 0
        },
        {
            "id": 39,
            "index": 811,
            "char": "'",
            "width": 10,
            "height": 12,
            "xoffset": 1,
            "yoffset": 26,
            "xadvance": 10,
            "chnl": 15,
            "x": 65,
            "y": 130,
            "page": 0
        },
        {
            "id": 46,
            "index": 770,
            "char": ".",
            "width": 9,
            "height": 9,
            "xoffset": 5,
            "yoffset": 58,
            "xadvance": 18,
            "chnl": 15,
            "x": 492,
            "y": 285,
            "page": 0
        },
        {
            "id": 32,
            "index": 3,
            "char": " ",
            "width": 0,
            "height": 0,
            "xoffset": -2,
            "yoffset": 62,
            "xadvance": 16,
            "chnl": 15,
            "x": 122,
            "y": 70,
            "page": 0
        }
    ],
    "info": {
        "face": "ComforterBrush-Regular",
        "size": 64,
        "bold": 0,
        "italic": 0,
        "charset": [
            " ",
            "!",
            "\"",
            "#",
            "$",
            "%",
            "&",
            "'",
            "(",
            ")",
            "*",
            "+",
            ",",
            "-",
            ".",
            "/",
            "0",
            "1",
            "2",
            "3",
            "4",
            "5",
            "6",
            "7",
            "8",
            "9",
            ":",
            ";",
            "<",
            "=",
            ">",
            "?",
            "@",
            "A",
            "B",
            "C",
            "D",
            "E",
            "F",
            "G",
            "H",
            "I",
            "J",
            "K",
            "L",
            "M",
            "N",
            "O",
            "P",
            "Q",
            "R",
            "S",
            "T",
            "U",
            "V",
            "W",
            "X",
            "Y",
            "Z",
            "[",
            "\\",
            "]",
            "^",
            "_",
            "`",
            "a",
            "b",
            "c",
            "d",
            "e",
            "f",
            "g",
            "h",
            "i",
            "j",
            "k",
            "l",
            "m",
            "n",
            "o",
            "p",
            "q",
            "r",
            "s",
            "t",
            "u",
            "v",
            "w",
            "x",
            "y",
            "z",
            "{",
            "|",
            "}",
            "~"
        ],
        "unicode": 1,
        "stretchH": 100,
        "smooth": 1,
        "aa": 1,
        "padding": [
            2,
            2,
            2,
            2
        ],
        "spacing": [
            0,
            0
        ],
        "outline": 0
    },
    "common": {
        "lineHeight": 90,
        "base": 62,
        "scaleW": 512,
        "scaleH": 512,
        "pages": 1,
        "packed": 0,
        "alphaChnl": 0,
        "redChnl": 0,
        "greenChnl": 0,
        "blueChnl": 0
    },
    "distanceField": {
        "fieldType": "msdf",
        "distanceRange": 4
    },
    "kernings": [
        {
            "first": 32,
            "second": 97,
            "amount": -2
        },
        {
            "first": 40,
            "second": 41,
            "amount": 9
        },
        {
            "first": 65,
            "second": 66,
            "amount": 4
        },
        {
            "first": 65,
            "second": 102,
            "amount": -2
        },
        {
            "first": 66,
            "second": 67,
            "amount": 4
        },
        {
            "first": 66,
            "second": 97,
            "amount": 2
        },
        {
            "first": 66,
            "second": 98,
            "amount": 2
        },
        {
            "first": 67,
            "second": 68,
            "amount": 10
        },
        {
            "first": 67,
            "second": 108,
            "amount": 10
        },
        {
            "first": 67,
            "second": 111,
            "amount": -9
        },
        {
            "first": 69,
            "second": 98,
            "amount": 4
        },
        {
            "first": 69,
            "second": 102,
            "amount": 2
        },
        {
            "first": 69,
            "second": 104,
            "amount": 2
        },
        {
            "first": 69,
            "second": 106,
            "amount": 5
        },
        {
            "first": 69,
            "second": 107,
            "amount": 2
        },
        {
            "first": 69,
            "second": 108,
            "amount": 2
        },
        {
            "first": 69,
            "second": 112,
            "amount": 4
        },
        {
            "first": 69,
            "second": 113,
            "amount": -4
        },
        {
            "first": 69,
            "second": 115,
            "amount": -2
        },
        {
            "first": 69,
            "second": 116,
            "amount": 1
        },
        {
            "first": 69,
            "second": 119,
            "amount": -4
        },
        {
            "first": 69,
            "second": 120,
            "amount": 6
        },
        {
            "first": 69,
            "second": 122,
            "amount": -4
        },
        {
            "first": 71,
            "second": 72,
            "amount": 6
        },
        {
            "first": 72,
            "second": 73,
            "amount": 9
        },
        {
            "first": 73,
            "second": 116,
            "amount": 4
        },
        {
            "first": 74,
            "second": 97,
            "amount": -4
        },
        {
            "first": 74,
            "second": 101,
            "amount": -2
        },
        {
            "first": 74,
            "second": 106,
            "amount": 4
        },
        {
            "first": 74,
            "second": 107,
            "amount": 1
        },
        {
            "first": 74,
            "second": 108,
            "amount": 1
        },
        {
            "first": 74,
            "second": 109,
            "amount": 2
        },
        {
            "first": 74,
            "second": 110,
            "amount": 4
        },
        {
            "first": 74,
            "second": 111,
            "amount": -3
        },
        {
            "first": 75,
            "second": 107,
            "amount": 1
        },
        {
            "first": 76,
            "second": 77,
            "amount": 6
        },
        {
            "first": 76,
            "second": 108,
            "amount": 4
        },
        {
            "first": 78,
            "second": 65,
            "amount": 1
        },
        {
            "first": 78,
            "second": 79,
            "amount": 2
        },
        {
            "first": 79,
            "second": 77,
            "amount": -2
        },
        {
            "first": 80,
            "second": 97,
            "amount": -6
        },
        {
            "first": 80,
            "second": 112,
            "amount": 6
        },
        {
            "first": 81,
            "second": 113,
            "amount": -1
        },
        {
            "first": 82,
            "second": 83,
            "amount": 4
        },
        {
            "first": 83,
            "second": 116,
            "amount": 5
        },
        {
            "first": 84,
            "second": 85,
            "amount": 26
        },
        {
            "first": 84,
            "second": 116,
            "amount": 22
        },
        {
            "first": 85,
            "second": 86,
            "amount": 3
        },
        {
            "first": 85,
            "second": 109,
            "amount": 3
        },
        {
            "first": 85,
            "second": 110,
            "amount": 3
        },
        {
            "first": 86,
            "second": 87,
            "amount": 8
        },
        {
            "first": 87,
            "second": 88,
            "amount": 4
        },
        {
            "first": 89,
            "second": 90,
            "amount": 4
        },
        {
            "first": 90,
            "second": 90,
            "amount": -2
        },
        {
            "first": 90,
            "second": 101,
            "amount": -1
        },
        {
            "first": 97,
            "second": 98,
            "amount": 3
        },
        {
            "first": 97,
            "second": 99,
            "amount": 2
        },
        {
            "first": 97,
            "second": 100,
            "amount": 4
        },
        {
            "first": 97,
            "second": 107,
            "amount": 5
        },
        {
            "first": 97,
            "second": 110,
            "amount": 3
        },
        {
            "first": 97,
            "second": 111,
            "amount": 1
        },
        {
            "first": 97,
            "second": 115,
            "amount": 2
        },
        {
            "first": 97,
            "second": 118,
            "amount": 3
        },
        {
            "first": 98,
            "second": 97,
            "amount": -1
        },
        {
            "first": 98,
            "second": 111,
            "amount": -1
        },
        {
            "first": 98,
            "second": 114,
            "amount": -2
        },
        {
            "first": 99,
            "second": 111,
            "amount": -1
        },
        {
            "first": 100,
            "second": 69,
            "amount": 4
        },
        {
            "first": 100,
            "second": 101,
            "amount": 2
        },
        {
            "first": 100,
            "second": 112,
            "amount": 5
        },
        {
            "first": 100,
            "second": 115,
            "amount": 2
        },
        {
            "first": 100,
            "second": 118,
            "amount": 3
        },
        {
            "first": 101,
            "second": 70,
            "amount": 4
        },
        {
            "first": 101,
            "second": 98,
            "amount": 1
        },
        {
            "first": 101,
            "second": 102,
            "amount": 3
        },
        {
            "first": 101,
            "second": 109,
            "amount": 2
        },
        {
            "first": 101,
            "second": 110,
            "amount": 1
        },
        {
            "first": 101,
            "second": 112,
            "amount": 1
        },
        {
            "first": 102,
            "second": 71,
            "amount": 11
        },
        {
            "first": 102,
            "second": 103,
            "amount": 3
        },
        {
            "first": 102,
            "second": 105,
            "amount": 3
        },
        {
            "first": 102,
            "second": 111,
            "amount": -1
        },
        {
            "first": 102,
            "second": 117,
            "amount": 2
        },
        {
            "first": 103,
            "second": 72,
            "amount": 8
        },
        {
            "first": 103,
            "second": 111,
            "amount": -1
        },
        {
            "first": 104,
            "second": 73,
            "amount": 7
        },
        {
            "first": 104,
            "second": 105,
            "amount": 2
        },
        {
            "first": 104,
            "second": 111,
            "amount": -3
        },
        {
            "first": 105,
            "second": 110,
            "amount": 2
        },
        {
            "first": 105,
            "second": 116,
            "amount": 1
        },
        {
            "first": 106,
            "second": 107,
            "amount": 4
        },
        {
            "first": 106,
            "second": 111,
            "amount": -2
        },
        {
            "first": 107,
            "second": 76,
            "amount": 7
        },
        {
            "first": 107,
            "second": 101,
            "amount": 0
        },
        {
            "first": 107,
            "second": 108,
            "amount": 1
        },
        {
            "first": 107,
            "second": 115,
            "amount": 1
        },
        {
            "first": 108,
            "second": 97,
            "amount": -3
        },
        {
            "first": 108,
            "second": 101,
            "amount": -1
        },
        {
            "first": 108,
            "second": 109,
            "amount": 2
        },
        {
            "first": 108,
            "second": 111,
            "amount": -3
        },
        {
            "first": 108,
            "second": 112,
            "amount": 3
        },
        {
            "first": 108,
            "second": 115,
            "amount": -3
        },
        {
            "first": 108,
            "second": 117,
            "amount": 2
        },
        {
            "first": 109,
            "second": 112,
            "amount": -2
        },
        {
            "first": 110,
            "second": 84,
            "amount": -19
        },
        {
            "first": 110,
            "second": 107,
            "amount": -1
        },
        {
            "first": 110,
            "second": 111,
            "amount": -2
        },
        {
            "first": 110,
            "second": 112,
            "amount": -2
        },
        {
            "first": 110,
            "second": 113,
            "amount": -2
        },
        {
            "first": 111,
            "second": 44,
            "amount": -8
        },
        {
            "first": 111,
            "second": 97,
            "amount": -4
        },
        {
            "first": 111,
            "second": 99,
            "amount": -3
        },
        {
            "first": 111,
            "second": 100,
            "amount": -3
        },
        {
            "first": 111,
            "second": 101,
            "amount": -2
        },
        {
            "first": 111,
            "second": 103,
            "amount": -3
        },
        {
            "first": 111,
            "second": 105,
            "amount": -1
        },
        {
            "first": 111,
            "second": 108,
            "amount": -4
        },
        {
            "first": 111,
            "second": 111,
            "amount": -4
        },
        {
            "first": 111,
            "second": 116,
            "amount": -3
        },
        {
            "first": 111,
            "second": 119,
            "amount": -5
        },
        {
            "first": 112,
            "second": 115,
            "amount": 2
        },
        {
            "first": 113,
            "second": 82,
            "amount": 3
        },
        {
            "first": 113,
            "second": 115,
            "amount": 2
        },
        {
            "first": 114,
            "second": 121,
            "amount": 2
        },
        {
            "first": 115,
            "second": 101,
            "amount": -1
        },
        {
            "first": 115,
            "second": 107,
            "amount": 1
        },
        {
            "first": 115,
            "second": 112,
            "amount": 0
        },
        {
            "first": 115,
            "second": 115,
            "amount": -2
        },
        {
            "first": 115,
            "second": 117,
            "amount": -2
        },
        {
            "first": 115,
            "second": 118,
            "amount": 2
        },
        {
            "first": 115,
            "second": 120,
            "amount": -2
        },
        {
            "first": 115,
            "second": 122,
            "amount": -2
        },
        {
            "first": 116,
            "second": 39,
            "amount": 1
        },
        {
            "first": 116,
            "second": 85,
            "amount": 13
        },
        {
            "first": 116,
            "second": 101,
            "amount": -2
        },
        {
            "first": 116,
            "second": 112,
            "amount": 2
        },
        {
            "first": 116,
            "second": 121,
            "amount": 1
        },
        {
            "first": 117,
            "second": 86,
            "amount": -7
        },
        {
            "first": 117,
            "second": 111,
            "amount": -3
        },
        {
            "first": 117,
            "second": 115,
            "amount": -1
        },
        {
            "first": 118,
            "second": 97,
            "amount": -2
        },
        {
            "first": 120,
            "second": 111,
            "amount": 1
        },
        {
            "first": 121,
            "second": 112,
            "amount": 0
        },
        {
            "first": 122,
            "second": 115,
            "amount": 1
        },
        {
            "first": 122,
            "second": 121,
            "amount": 2
        },
        {
            "first": 122,
            "second": 122,
            "amount": -2
        }
    ]
}