{
    "pages": [
        "Arbutus-Regular.png"
    ],
    "chars": [
        {
            "id": 87,
            "index": 77,
            "char": "W",
            "width": 84,
            "height": 49,
            "xoffset": -2,
            "yoffset": 20,
            "xadvance": 80,
            "chnl": 15,
            "x": 0,
            "y": 0,
            "page": 0
        },
        {
            "id": 64,
            "index": 54,
            "char": "@",
            "width": 77,
            "height": 62,
            "xoffset": 2,
            "yoffset": 19,
            "xadvance": 80,
            "chnl": 15,
            "x": 0,
            "y": 50,
            "page": 0
        },
        {
            "id": 109,
            "index": 99,
            "char": "m",
            "width": 74,
            "height": 38,
            "xoffset": 2,
            "yoffset": 31,
            "xadvance": 75,
            "chnl": 15,
            "x": 78,
            "y": 50,
            "page": 0
        },
        {
            "id": 106,
            "index": 96,
            "char": "j",
            "width": 32,
            "height": 71,
            "xoffset": -7,
            "yoffset": 15,
            "xadvance": 27,
            "chnl": 15,
            "x": 153,
            "y": 0,
            "page": 0
        },
        {
            "id": 119,
            "index": 109,
            "char": "w",
            "width": 68,
            "height": 37,
            "xoffset": -2,
            "yoffset": 32,
            "xadvance": 64,
            "chnl": 15,
            "x": 78,
            "y": 89,
            "page": 0
        },
        {
            "id": 36,
            "index": 26,
            "char": "$",
            "width": 47,
            "height": 67,
            "xoffset": 4,
            "yoffset": 10,
            "xadvance": 53,
            "chnl": 15,
            "x": 186,
            "y": 0,
            "page": 0
        },
        {
            "id": 37,
            "index": 27,
            "char": "%",
            "width": 67,
            "height": 49,
            "xoffset": 1,
            "yoffset": 20,
            "xadvance": 69,
            "chnl": 15,
            "x": 85,
            "y": 0,
            "page": 0
        },
        {
            "id": 77,
            "index": 67,
            "char": "M",
            "width": 67,
            "height": 49,
            "xoffset": 1,
            "yoffset": 20,
            "xadvance": 69,
            "chnl": 15,
            "x": 186,
            "y": 68,
            "page": 0
        },
        {
            "id": 103,
            "index": 93,
            "char": "g",
            "width": 46,
            "height": 66,
            "xoffset": 2,
            "yoffset": 20,
            "xadvance": 48,
            "chnl": 15,
            "x": 0,
            "y": 113,
            "page": 0
        },
        {
            "id": 91,
            "index": 81,
            "char": "[",
            "width": 25,
            "height": 63,
            "xoffset": 4,
            "yoffset": 13,
            "xadvance": 32,
            "chnl": 15,
            "x": 47,
            "y": 113,
            "page": 0
        },
        {
            "id": 93,
            "index": 83,
            "char": "]",
            "width": 25,
            "height": 63,
            "xoffset": 3,
            "yoffset": 13,
            "xadvance": 32,
            "chnl": 15,
            "x": 153,
            "y": 72,
            "page": 0
        },
        {
            "id": 40,
            "index": 30,
            "char": "(",
            "width": 28,
            "height": 62,
            "xoffset": 1,
            "yoffset": 13,
            "xadvance": 32,
            "chnl": 15,
            "x": 0,
            "y": 180,
            "page": 0
        },
        {
            "id": 41,
            "index": 31,
            "char": ")",
            "width": 28,
            "height": 62,
            "xoffset": 3,
            "yoffset": 13,
            "xadvance": 32,
            "chnl": 15,
            "x": 29,
            "y": 180,
            "page": 0
        },
        {
            "id": 81,
            "index": 71,
            "char": "Q",
            "width": 54,
            "height": 62,
            "xoffset": 1,
            "yoffset": 19,
            "xadvance": 53,
            "chnl": 15,
            "x": 58,
            "y": 177,
            "page": 0
        },
        {
            "id": 123,
            "index": 113,
            "char": "{",
            "width": 27,
            "height": 62,
            "xoffset": 2,
            "yoffset": 13,
            "xadvance": 32,
            "chnl": 15,
            "x": 113,
            "y": 127,
            "page": 0
        },
        {
            "id": 125,
            "index": 115,
            "char": "}",
            "width": 27,
            "height": 62,
            "xoffset": 3,
            "yoffset": 13,
            "xadvance": 32,
            "chnl": 15,
            "x": 113,
            "y": 190,
            "page": 0
        },
        {
            "id": 124,
            "index": 114,
            "char": "|",
            "width": 16,
            "height": 61,
            "xoffset": 3,
            "yoffset": 13,
            "xadvance": 21,
            "chnl": 15,
            "x": 234,
            "y": 0,
            "page": 0
        },
        {
            "id": 47,
            "index": 37,
            "char": "/",
            "width": 34,
            "height": 59,
            "xoffset": -1,
            "yoffset": 14,
            "xadvance": 32,
            "chnl": 15,
            "x": 179,
            "y": 118,
            "page": 0
        },
        {
            "id": 72,
            "index": 62,
            "char": "H",
            "width": 59,
            "height": 49,
            "xoffset": 0,
            "yoffset": 20,
            "xadvance": 59,
            "chnl": 15,
            "x": 141,
            "y": 178,
            "page": 0
        },
        {
            "id": 92,
            "index": 82,
            "char": "\\",
            "width": 34,
            "height": 59,
            "xoffset": -1,
            "yoffset": 14,
            "xadvance": 32,
            "chnl": 15,
            "x": 214,
            "y": 118,
            "page": 0
        },
        {
            "id": 78,
            "index": 68,
            "char": "N",
            "width": 58,
            "height": 49,
            "xoffset": 1,
            "yoffset": 20,
            "xadvance": 59,
            "chnl": 15,
            "x": 251,
            "y": 0,
            "page": 0
        },
        {
            "id": 84,
            "index": 74,
            "char": "T",
            "width": 58,
            "height": 49,
            "xoffset": 0,
            "yoffset": 20,
            "xadvance": 59,
            "chnl": 15,
            "x": 201,
            "y": 178,
            "page": 0
        },
        {
            "id": 65,
            "index": 55,
            "char": "A",
            "width": 57,
            "height": 49,
            "xoffset": -2,
            "yoffset": 20,
            "xadvance": 53,
            "chnl": 15,
            "x": 249,
            "y": 118,
            "page": 0
        },
        {
            "id": 75,
            "index": 65,
            "char": "K",
            "width": 57,
            "height": 49,
            "xoffset": 1,
            "yoffset": 20,
            "xadvance": 59,
            "chnl": 15,
            "x": 254,
            "y": 50,
            "page": 0
        },
        {
            "id": 86,
            "index": 76,
            "char": "V",
            "width": 57,
            "height": 49,
            "xoffset": -2,
            "yoffset": 20,
            "xadvance": 53,
            "chnl": 15,
            "x": 310,
            "y": 0,
            "page": 0
        },
        {
            "id": 89,
            "index": 79,
            "char": "Y",
            "width": 57,
            "height": 49,
            "xoffset": -2,
            "yoffset": 20,
            "xadvance": 53,
            "chnl": 15,
            "x": 260,
            "y": 168,
            "page": 0
        },
        {
            "id": 102,
            "index": 92,
            "char": "f",
            "width": 39,
            "height": 56,
            "xoffset": 1,
            "yoffset": 13,
            "xadvance": 37,
            "chnl": 15,
            "x": 307,
            "y": 100,
            "page": 0
        },
        {
            "id": 85,
            "index": 75,
            "char": "U",
            "width": 55,
            "height": 50,
            "xoffset": 2,
            "yoffset": 20,
            "xadvance": 59,
            "chnl": 15,
            "x": 318,
            "y": 157,
            "page": 0
        },
        {
            "id": 88,
            "index": 78,
            "char": "X",
            "width": 55,
            "height": 49,
            "xoffset": -1,
            "yoffset": 20,
            "xadvance": 53,
            "chnl": 15,
            "x": 312,
            "y": 50,
            "page": 0
        },
        {
            "id": 98,
            "index": 88,
            "char": "b",
            "width": 48,
            "height": 55,
            "xoffset": 3,
            "yoffset": 14,
            "xadvance": 53,
            "chnl": 15,
            "x": 347,
            "y": 100,
            "page": 0
        },
        {
            "id": 100,
            "index": 90,
            "char": "d",
            "width": 46,
            "height": 55,
            "xoffset": 2,
            "yoffset": 14,
            "xadvance": 48,
            "chnl": 15,
            "x": 368,
            "y": 0,
            "page": 0
        },
        {
            "id": 104,
            "index": 94,
            "char": "h",
            "width": 51,
            "height": 55,
            "xoffset": 2,
            "yoffset": 14,
            "xadvance": 53,
            "chnl": 15,
            "x": 374,
            "y": 156,
            "page": 0
        },
        {
            "id": 107,
            "index": 97,
            "char": "k",
            "width": 51,
            "height": 55,
            "xoffset": 1,
            "yoffset": 14,
            "xadvance": 53,
            "chnl": 15,
            "x": 426,
            "y": 0,
            "page": 0
        },
        {
            "id": 108,
            "index": 98,
            "char": "l",
            "width": 27,
            "height": 55,
            "xoffset": 1,
            "yoffset": 14,
            "xadvance": 27,
            "chnl": 15,
            "x": 478,
            "y": 0,
            "page": 0
        },
        {
            "id": 112,
            "index": 102,
            "char": "p",
            "width": 47,
            "height": 55,
            "xoffset": 2,
            "yoffset": 31,
            "xadvance": 48,
            "chnl": 15,
            "x": 426,
            "y": 56,
            "page": 0
        },
        {
            "id": 113,
            "index": 103,
            "char": "q",
            "width": 51,
            "height": 55,
            "xoffset": 2,
            "yoffset": 31,
            "xadvance": 53,
            "chnl": 15,
            "x": 426,
            "y": 112,
            "page": 0
        },
        {
            "id": 121,
            "index": 111,
            "char": "y",
            "width": 48,
            "height": 55,
            "xoffset": -2,
            "yoffset": 32,
            "xadvance": 43,
            "chnl": 15,
            "x": 426,
            "y": 168,
            "page": 0
        },
        {
            "id": 38,
            "index": 28,
            "char": "&",
            "width": 54,
            "height": 49,
            "xoffset": 2,
            "yoffset": 20,
            "xadvance": 58,
            "chnl": 15,
            "x": 58,
            "y": 240,
            "page": 0
        },
        {
            "id": 105,
            "index": 95,
            "char": "i",
            "width": 29,
            "height": 54,
            "xoffset": -1,
            "yoffset": 15,
            "xadvance": 27,
            "chnl": 15,
            "x": 396,
            "y": 56,
            "page": 0
        },
        {
            "id": 68,
            "index": 58,
            "char": "D",
            "width": 53,
            "height": 49,
            "xoffset": 1,
            "yoffset": 20,
            "xadvance": 53,
            "chnl": 15,
            "x": 318,
            "y": 208,
            "page": 0
        },
        {
            "id": 82,
            "index": 72,
            "char": "R",
            "width": 53,
            "height": 49,
            "xoffset": 1,
            "yoffset": 20,
            "xadvance": 53,
            "chnl": 15,
            "x": 372,
            "y": 212,
            "page": 0
        },
        {
            "id": 95,
            "index": 85,
            "char": "_",
            "width": 53,
            "height": 10,
            "xoffset": -3,
            "yoffset": 71,
            "xadvance": 48,
            "chnl": 15,
            "x": 0,
            "y": 243,
            "page": 0
        },
        {
            "id": 71,
            "index": 61,
            "char": "G",
            "width": 52,
            "height": 50,
            "xoffset": 1,
            "yoffset": 19,
            "xadvance": 53,
            "chnl": 15,
            "x": 260,
            "y": 218,
            "page": 0
        },
        {
            "id": 79,
            "index": 69,
            "char": "O",
            "width": 52,
            "height": 50,
            "xoffset": 1,
            "yoffset": 19,
            "xadvance": 53,
            "chnl": 15,
            "x": 0,
            "y": 254,
            "page": 0
        },
        {
            "id": 67,
            "index": 57,
            "char": "C",
            "width": 51,
            "height": 50,
            "xoffset": 1,
            "yoffset": 19,
            "xadvance": 53,
            "chnl": 15,
            "x": 313,
            "y": 258,
            "page": 0
        },
        {
            "id": 110,
            "index": 100,
            "char": "n",
            "width": 51,
            "height": 38,
            "xoffset": 2,
            "yoffset": 31,
            "xadvance": 53,
            "chnl": 15,
            "x": 426,
            "y": 224,
            "page": 0
        },
        {
            "id": 35,
            "index": 25,
            "char": "#",
            "width": 50,
            "height": 49,
            "xoffset": 2,
            "yoffset": 20,
            "xadvance": 53,
            "chnl": 15,
            "x": 365,
            "y": 262,
            "page": 0
        },
        {
            "id": 48,
            "index": 38,
            "char": "0",
            "width": 49,
            "height": 50,
            "xoffset": 2,
            "yoffset": 19,
            "xadvance": 53,
            "chnl": 15,
            "x": 416,
            "y": 263,
            "page": 0
        },
        {
            "id": 50,
            "index": 40,
            "char": "2",
            "width": 46,
            "height": 50,
            "xoffset": 2,
            "yoffset": 20,
            "xadvance": 48,
            "chnl": 15,
            "x": 466,
            "y": 263,
            "page": 0
        },
        {
            "id": 51,
            "index": 41,
            "char": "3",
            "width": 46,
            "height": 50,
            "xoffset": 1,
            "yoffset": 20,
            "xadvance": 48,
            "chnl": 15,
            "x": 141,
            "y": 228,
            "page": 0
        },
        {
            "id": 54,
            "index": 44,
            "char": "6",
            "width": 47,
            "height": 50,
            "xoffset": 0,
            "yoffset": 20,
            "xadvance": 48,
            "chnl": 15,
            "x": 188,
            "y": 228,
            "page": 0
        },
        {
            "id": 56,
            "index": 46,
            "char": "8",
            "width": 48,
            "height": 50,
            "xoffset": 0,
            "yoffset": 20,
            "xadvance": 48,
            "chnl": 15,
            "x": 236,
            "y": 269,
            "page": 0
        },
        {
            "id": 57,
            "index": 47,
            "char": "9",
            "width": 46,
            "height": 50,
            "xoffset": 1,
            "yoffset": 20,
            "xadvance": 48,
            "chnl": 15,
            "x": 285,
            "y": 309,
            "page": 0
        },
        {
            "id": 83,
            "index": 73,
            "char": "S",
            "width": 47,
            "height": 50,
            "xoffset": 1,
            "yoffset": 19,
            "xadvance": 48,
            "chnl": 15,
            "x": 332,
            "y": 312,
            "page": 0
        },
        {
            "id": 117,
            "index": 107,
            "char": "u",
            "width": 50,
            "height": 38,
            "xoffset": 0,
            "yoffset": 31,
            "xadvance": 48,
            "chnl": 15,
            "x": 113,
            "y": 279,
            "page": 0
        },
        {
            "id": 33,
            "index": 23,
            "char": "!",
            "width": 21,
            "height": 49,
            "xoffset": 0,
            "yoffset": 20,
            "xadvance": 22,
            "chnl": 15,
            "x": 73,
            "y": 127,
            "page": 0
        },
        {
            "id": 49,
            "index": 39,
            "char": "1",
            "width": 33,
            "height": 49,
            "xoffset": 0,
            "yoffset": 20,
            "xadvance": 32,
            "chnl": 15,
            "x": 478,
            "y": 56,
            "page": 0
        },
        {
            "id": 52,
            "index": 42,
            "char": "4",
            "width": 49,
            "height": 49,
            "xoffset": -1,
            "yoffset": 20,
            "xadvance": 48,
            "chnl": 15,
            "x": 53,
            "y": 290,
            "page": 0
        },
        {
            "id": 53,
            "index": 43,
            "char": "5",
            "width": 45,
            "height": 49,
            "xoffset": 2,
            "yoffset": 20,
            "xadvance": 48,
            "chnl": 15,
            "x": 0,
            "y": 305,
            "page": 0
        },
        {
            "id": 55,
            "index": 45,
            "char": "7",
            "width": 46,
            "height": 49,
            "xoffset": -1,
            "yoffset": 20,
            "xadvance": 43,
            "chnl": 15,
            "x": 164,
            "y": 279,
            "page": 0
        },
        {
            "id": 63,
            "index": 53,
            "char": "?",
            "width": 39,
            "height": 49,
            "xoffset": 1,
            "yoffset": 20,
            "xadvance": 43,
            "chnl": 15,
            "x": 103,
            "y": 318,
            "page": 0
        },
        {
            "id": 66,
            "index": 56,
            "char": "B",
            "width": 48,
            "height": 49,
            "xoffset": 1,
            "yoffset": 20,
            "xadvance": 48,
            "chnl": 15,
            "x": 46,
            "y": 340,
            "page": 0
        },
        {
            "id": 69,
            "index": 59,
            "char": "E",
            "width": 46,
            "height": 49,
            "xoffset": 1,
            "yoffset": 20,
            "xadvance": 48,
            "chnl": 15,
            "x": 211,
            "y": 320,
            "page": 0
        },
        {
            "id": 70,
            "index": 60,
            "char": "F",
            "width": 47,
            "height": 49,
            "xoffset": 1,
            "yoffset": 20,
            "xadvance": 48,
            "chnl": 15,
            "x": 143,
            "y": 329,
            "page": 0
        },
        {
            "id": 73,
            "index": 63,
            "char": "I",
            "width": 30,
            "height": 49,
            "xoffset": 1,
            "yoffset": 20,
            "xadvance": 32,
            "chnl": 15,
            "x": 478,
            "y": 106,
            "page": 0
        },
        {
            "id": 74,
            "index": 64,
            "char": "J",
            "width": 45,
            "height": 49,
            "xoffset": 0,
            "yoffset": 20,
            "xadvance": 43,
            "chnl": 15,
            "x": 0,
            "y": 355,
            "page": 0
        },
        {
            "id": 76,
            "index": 66,
            "char": "L",
            "width": 48,
            "height": 49,
            "xoffset": 1,
            "yoffset": 20,
            "xadvance": 48,
            "chnl": 15,
            "x": 258,
            "y": 360,
            "page": 0
        },
        {
            "id": 80,
            "index": 70,
            "char": "P",
            "width": 47,
            "height": 49,
            "xoffset": 1,
            "yoffset": 20,
            "xadvance": 48,
            "chnl": 15,
            "x": 95,
            "y": 368,
            "page": 0
        },
        {
            "id": 90,
            "index": 80,
            "char": "Z",
            "width": 48,
            "height": 49,
            "xoffset": 0,
            "yoffset": 20,
            "xadvance": 48,
            "chnl": 15,
            "x": 46,
            "y": 390,
            "page": 0
        },
        {
            "id": 118,
            "index": 108,
            "char": "v",
            "width": 48,
            "height": 37,
            "xoffset": -3,
            "yoffset": 32,
            "xadvance": 43,
            "chnl": 15,
            "x": 191,
            "y": 370,
            "page": 0
        },
        {
            "id": 116,
            "index": 106,
            "char": "t",
            "width": 36,
            "height": 47,
            "xoffset": 1,
            "yoffset": 22,
            "xadvance": 37,
            "chnl": 15,
            "x": 475,
            "y": 168,
            "page": 0
        },
        {
            "id": 126,
            "index": 116,
            "char": "~",
            "width": 47,
            "height": 24,
            "xoffset": 1,
            "yoffset": 30,
            "xadvance": 48,
            "chnl": 15,
            "x": 143,
            "y": 379,
            "page": 0
        },
        {
            "id": 59,
            "index": 49,
            "char": ";",
            "width": 20,
            "height": 46,
            "xoffset": 1,
            "yoffset": 32,
            "xadvance": 21,
            "chnl": 15,
            "x": 478,
            "y": 216,
            "page": 0
        },
        {
            "id": 60,
            "index": 50,
            "char": "<",
            "width": 39,
            "height": 44,
            "xoffset": 2,
            "yoffset": 25,
            "xadvance": 48,
            "chnl": 15,
            "x": 0,
            "y": 405,
            "page": 0
        },
        {
            "id": 62,
            "index": 52,
            "char": ">",
            "width": 39,
            "height": 44,
            "xoffset": 7,
            "yoffset": 25,
            "xadvance": 48,
            "chnl": 15,
            "x": 143,
            "y": 404,
            "page": 0
        },
        {
            "id": 94,
            "index": 84,
            "char": "^",
            "width": 44,
            "height": 39,
            "xoffset": 2,
            "yoffset": 14,
            "xadvance": 48,
            "chnl": 15,
            "x": 95,
            "y": 418,
            "page": 0
        },
        {
            "id": 97,
            "index": 87,
            "char": "a",
            "width": 44,
            "height": 38,
            "xoffset": 0,
            "yoffset": 31,
            "xadvance": 43,
            "chnl": 15,
            "x": 40,
            "y": 440,
            "page": 0
        },
        {
            "id": 111,
            "index": 101,
            "char": "o",
            "width": 44,
            "height": 38,
            "xoffset": 2,
            "yoffset": 31,
            "xadvance": 48,
            "chnl": 15,
            "x": 85,
            "y": 458,
            "page": 0
        },
        {
            "id": 120,
            "index": 110,
            "char": "x",
            "width": 43,
            "height": 37,
            "xoffset": 0,
            "yoffset": 32,
            "xadvance": 43,
            "chnl": 15,
            "x": 130,
            "y": 458,
            "page": 0
        },
        {
            "id": 114,
            "index": 104,
            "char": "r",
            "width": 41,
            "height": 38,
            "xoffset": 1,
            "yoffset": 31,
            "xadvance": 43,
            "chnl": 15,
            "x": 174,
            "y": 449,
            "page": 0
        },
        {
            "id": 122,
            "index": 112,
            "char": "z",
            "width": 41,
            "height": 38,
            "xoffset": 2,
            "yoffset": 31,
            "xadvance": 43,
            "chnl": 15,
            "x": 183,
            "y": 410,
            "page": 0
        },
        {
            "id": 34,
            "index": 24,
            "char": "\"",
            "width": 40,
            "height": 24,
            "xoffset": 1,
            "yoffset": 14,
            "xadvance": 43,
            "chnl": 15,
            "x": 174,
            "y": 488,
            "page": 0
        },
        {
            "id": 99,
            "index": 89,
            "char": "c",
            "width": 40,
            "height": 39,
            "xoffset": 1,
            "yoffset": 31,
            "xadvance": 42,
            "chnl": 15,
            "x": 216,
            "y": 449,
            "page": 0
        },
        {
            "id": 101,
            "index": 91,
            "char": "e",
            "width": 40,
            "height": 38,
            "xoffset": 1,
            "yoffset": 31,
            "xadvance": 43,
            "chnl": 15,
            "x": 225,
            "y": 410,
            "page": 0
        },
        {
            "id": 43,
            "index": 33,
            "char": "+",
            "width": 39,
            "height": 39,
            "xoffset": 2,
            "yoffset": 26,
            "xadvance": 43,
            "chnl": 15,
            "x": 0,
            "y": 450,
            "page": 0
        },
        {
            "id": 61,
            "index": 51,
            "char": "=",
            "width": 39,
            "height": 29,
            "xoffset": 2,
            "yoffset": 32,
            "xadvance": 43,
            "chnl": 15,
            "x": 40,
            "y": 479,
            "page": 0
        },
        {
            "id": 42,
            "index": 32,
            "char": "*",
            "width": 38,
            "height": 38,
            "xoffset": 0,
            "yoffset": 10,
            "xadvance": 37,
            "chnl": 15,
            "x": 257,
            "y": 449,
            "page": 0
        },
        {
            "id": 115,
            "index": 105,
            "char": "s",
            "width": 38,
            "height": 38,
            "xoffset": 0,
            "yoffset": 31,
            "xadvance": 37,
            "chnl": 15,
            "x": 266,
            "y": 410,
            "page": 0
        },
        {
            "id": 58,
            "index": 48,
            "char": ":",
            "width": 20,
            "height": 37,
            "xoffset": 1,
            "yoffset": 32,
            "xadvance": 21,
            "chnl": 15,
            "x": 285,
            "y": 269,
            "page": 0
        },
        {
            "id": 45,
            "index": 35,
            "char": "-",
            "width": 30,
            "height": 16,
            "xoffset": 1,
            "yoffset": 39,
            "xadvance": 32,
            "chnl": 15,
            "x": 130,
            "y": 496,
            "page": 0
        },
        {
            "id": 44,
            "index": 34,
            "char": ",",
            "width": 20,
            "height": 28,
            "xoffset": 1,
            "yoffset": 52,
            "xadvance": 21,
            "chnl": 15,
            "x": 236,
            "y": 228,
            "page": 0
        },
        {
            "id": 39,
            "index": 29,
            "char": "'",
            "width": 20,
            "height": 24,
            "xoffset": 1,
            "yoffset": 14,
            "xadvance": 21,
            "chnl": 15,
            "x": 257,
            "y": 488,
            "page": 0
        },
        {
            "id": 96,
            "index": 86,
            "char": "`",
            "width": 23,
            "height": 19,
            "xoffset": -1,
            "yoffset": 13,
            "xadvance": 32,
            "chnl": 15,
            "x": 211,
            "y": 279,
            "page": 0
        },
        {
            "id": 46,
            "index": 36,
            "char": ".",
            "width": 20,
            "height": 17,
            "xoffset": 1,
            "yoffset": 52,
            "xadvance": 21,
            "chnl": 15,
            "x": 254,
            "y": 100,
            "page": 0
        },
        {
            "id": 32,
            "index": 22,
            "char": " ",
            "width": 0,
            "height": 0,
            "xoffset": -2,
            "yoffset": 65,
            "xadvance": 26,
            "chnl": 15,
            "x": 347,
            "y": 156,
            "page": 0
        }
    ],
    "info": {
        "face": "Arbutus-Regular",
        "size": 64,
        "bold": 0,
        "italic": 0,
        "charset": [
            " ",
            "!",
            "\"",
            "#",
            "$",
            "%",
            "&",
            "'",
            "(",
            ")",
            "*",
            "+",
            ",",
            "-",
            ".",
            "/",
            "0",
            "1",
            "2",
            "3",
            "4",
            "5",
            "6",
            "7",
            "8",
            "9",
            ":",
            ";",
            "<",
            "=",
            ">",
            "?",
            "@",
            "A",
            "B",
            "C",
            "D",
            "E",
            "F",
            "G",
            "H",
            "I",
            "J",
            "K",
            "L",
            "M",
            "N",
            "O",
            "P",
            "Q",
            "R",
            "S",
            "T",
            "U",
            "V",
            "W",
            "X",
            "Y",
            "Z",
            "[",
            "\\",
            "]",
            "^",
            "_",
            "`",
            "a",
            "b",
            "c",
            "d",
            "e",
            "f",
            "g",
            "h",
            "i",
            "j",
            "k",
            "l",
            "m",
            "n",
            "o",
            "p",
            "q",
            "r",
            "s",
            "t",
            "u",
            "v",
            "w",
            "x",
            "y",
            "z",
            "{",
            "|",
            "}",
            "~"
        ],
        "unicode": 1,
        "stretchH": 100,
        "smooth": 1,
        "aa": 1,
        "padding": [
            2,
            2,
            2,
            2
        ],
        "spacing": [
            0,
            0
        ],
        "outline": 0
    },
    "common": {
        "lineHeight": 80,
        "base": 65,
        "scaleW": 512,
        "scaleH": 512,
        "pages": 1,
        "packed": 0,
        "alphaChnl": 0,
        "redChnl": 0,
        "greenChnl": 0,
        "blueChnl": 0
    },
    "distanceField": {
        "fieldType": "msdf",
        "distanceRange": 4
    },
    "kernings": []
}