{
    "pages": [
        "CutiveMono-Regular.png"
    ],
    "chars": [
        {
            "id": 36,
            "index": 376,
            "char": "$",
            "width": 29,
            "height": 51,
            "xoffset": 6,
            "yoffset": 13,
            "xadvance": 39,
            "chnl": 15,
            "x": 0,
            "y": 0,
            "page": 0
        },
        {
            "id": 123,
            "index": 352,
            "char": "{",
            "width": 19,
            "height": 51,
            "xoffset": 10,
            "yoffset": 15,
            "xadvance": 39,
            "chnl": 15,
            "x": 30,
            "y": 0,
            "page": 0
        },
        {
            "id": 125,
            "index": 353,
            "char": "}",
            "width": 19,
            "height": 51,
            "xoffset": 10,
            "yoffset": 15,
            "xadvance": 39,
            "chnl": 15,
            "x": 50,
            "y": 0,
            "page": 0
        },
        {
            "id": 91,
            "index": 354,
            "char": "[",
            "width": 14,
            "height": 50,
            "xoffset": 14,
            "yoffset": 13,
            "xadvance": 39,
            "chnl": 15,
            "x": 70,
            "y": 0,
            "page": 0
        },
        {
            "id": 93,
            "index": 355,
            "char": "]",
            "width": 14,
            "height": 50,
            "xoffset": 11,
            "yoffset": 13,
            "xadvance": 39,
            "chnl": 15,
            "x": 85,
            "y": 0,
            "page": 0
        },
        {
            "id": 106,
            "index": 208,
            "char": "j",
            "width": 23,
            "height": 50,
            "xoffset": 7,
            "yoffset": 18,
            "xadvance": 39,
            "chnl": 15,
            "x": 100,
            "y": 0,
            "page": 0
        },
        {
            "id": 35,
            "index": 343,
            "char": "#",
            "width": 29,
            "height": 49,
            "xoffset": 5,
            "yoffset": 14,
            "xadvance": 39,
            "chnl": 15,
            "x": 0,
            "y": 52,
            "page": 0
        },
        {
            "id": 40,
            "index": 356,
            "char": "(",
            "width": 13,
            "height": 49,
            "xoffset": 13,
            "yoffset": 15,
            "xadvance": 39,
            "chnl": 15,
            "x": 30,
            "y": 52,
            "page": 0
        },
        {
            "id": 41,
            "index": 357,
            "char": ")",
            "width": 13,
            "height": 49,
            "xoffset": 13,
            "yoffset": 15,
            "xadvance": 39,
            "chnl": 15,
            "x": 44,
            "y": 52,
            "page": 0
        },
        {
            "id": 81,
            "index": 86,
            "char": "Q",
            "width": 36,
            "height": 49,
            "xoffset": 1,
            "yoffset": 18,
            "xadvance": 39,
            "chnl": 15,
            "x": 70,
            "y": 51,
            "page": 0
        },
        {
            "id": 37,
            "index": 399,
            "char": "%",
            "width": 34,
            "height": 48,
            "xoffset": 2,
            "yoffset": 19,
            "xadvance": 39,
            "chnl": 15,
            "x": 107,
            "y": 51,
            "page": 0
        },
        {
            "id": 47,
            "index": 350,
            "char": "/",
            "width": 28,
            "height": 48,
            "xoffset": 6,
            "yoffset": 18,
            "xadvance": 39,
            "chnl": 15,
            "x": 124,
            "y": 0,
            "page": 0
        },
        {
            "id": 92,
            "index": 335,
            "char": "\\",
            "width": 28,
            "height": 48,
            "xoffset": 6,
            "yoffset": 18,
            "xadvance": 39,
            "chnl": 15,
            "x": 142,
            "y": 49,
            "page": 0
        },
        {
            "id": 124,
            "index": 411,
            "char": "|",
            "width": 8,
            "height": 47,
            "xoffset": 18,
            "yoffset": 16,
            "xadvance": 39,
            "chnl": 15,
            "x": 153,
            "y": 0,
            "page": 0
        },
        {
            "id": 53,
            "index": 321,
            "char": "5",
            "width": 26,
            "height": 44,
            "xoffset": 8,
            "yoffset": 16,
            "xadvance": 39,
            "chnl": 15,
            "x": 162,
            "y": 0,
            "page": 0
        },
        {
            "id": 54,
            "index": 322,
            "char": "6",
            "width": 28,
            "height": 44,
            "xoffset": 6,
            "yoffset": 16,
            "xadvance": 39,
            "chnl": 15,
            "x": 171,
            "y": 45,
            "page": 0
        },
        {
            "id": 75,
            "index": 58,
            "char": "K",
            "width": 44,
            "height": 41,
            "xoffset": -1,
            "yoffset": 18,
            "xadvance": 39,
            "chnl": 15,
            "x": 189,
            "y": 0,
            "page": 0
        },
        {
            "id": 57,
            "index": 325,
            "char": "9",
            "width": 28,
            "height": 43,
            "xoffset": 6,
            "yoffset": 18,
            "xadvance": 39,
            "chnl": 15,
            "x": 200,
            "y": 42,
            "page": 0
        },
        {
            "id": 38,
            "index": 404,
            "char": "&",
            "width": 34,
            "height": 42,
            "xoffset": 4,
            "yoffset": 18,
            "xadvance": 39,
            "chnl": 15,
            "x": 200,
            "y": 86,
            "page": 0
        },
        {
            "id": 48,
            "index": 316,
            "char": "0",
            "width": 28,
            "height": 42,
            "xoffset": 5,
            "yoffset": 18,
            "xadvance": 39,
            "chnl": 15,
            "x": 171,
            "y": 90,
            "page": 0
        },
        {
            "id": 51,
            "index": 319,
            "char": "3",
            "width": 25,
            "height": 42,
            "xoffset": 6,
            "yoffset": 18,
            "xadvance": 39,
            "chnl": 15,
            "x": 229,
            "y": 42,
            "page": 0
        },
        {
            "id": 56,
            "index": 324,
            "char": "8",
            "width": 28,
            "height": 42,
            "xoffset": 6,
            "yoffset": 18,
            "xadvance": 39,
            "chnl": 15,
            "x": 142,
            "y": 98,
            "page": 0
        },
        {
            "id": 64,
            "index": 403,
            "char": "@",
            "width": 39,
            "height": 42,
            "xoffset": 1,
            "yoffset": 21,
            "xadvance": 39,
            "chnl": 15,
            "x": 200,
            "y": 129,
            "page": 0
        },
        {
            "id": 67,
            "index": 16,
            "char": "C",
            "width": 36,
            "height": 42,
            "xoffset": 2,
            "yoffset": 18,
            "xadvance": 39,
            "chnl": 15,
            "x": 0,
            "y": 172,
            "page": 0
        },
        {
            "id": 71,
            "index": 37,
            "char": "G",
            "width": 39,
            "height": 42,
            "xoffset": 1,
            "yoffset": 18,
            "xadvance": 39,
            "chnl": 15,
            "x": 0,
            "y": 102,
            "page": 0
        },
        {
            "id": 77,
            "index": 66,
            "char": "M",
            "width": 42,
            "height": 41,
            "xoffset": -1,
            "yoffset": 18,
            "xadvance": 39,
            "chnl": 15,
            "x": 0,
            "y": 215,
            "page": 0
        },
        {
            "id": 79,
            "index": 73,
            "char": "O",
            "width": 36,
            "height": 42,
            "xoffset": 1,
            "yoffset": 18,
            "xadvance": 39,
            "chnl": 15,
            "x": 37,
            "y": 172,
            "page": 0
        },
        {
            "id": 83,
            "index": 91,
            "char": "S",
            "width": 29,
            "height": 42,
            "xoffset": 6,
            "yoffset": 18,
            "xadvance": 39,
            "chnl": 15,
            "x": 107,
            "y": 100,
            "page": 0
        },
        {
            "id": 86,
            "index": 111,
            "char": "V",
            "width": 38,
            "height": 42,
            "xoffset": 1,
            "yoffset": 18,
            "xadvance": 39,
            "chnl": 15,
            "x": 58,
            "y": 101,
            "page": 0
        },
        {
            "id": 103,
            "index": 189,
            "char": "g",
            "width": 32,
            "height": 42,
            "xoffset": 7,
            "yoffset": 28,
            "xadvance": 39,
            "chnl": 15,
            "x": 137,
            "y": 141,
            "page": 0
        },
        {
            "id": 119,
            "index": 293,
            "char": "w",
            "width": 42,
            "height": 29,
            "xoffset": -1,
            "yoffset": 31,
            "xadvance": 39,
            "chnl": 15,
            "x": 43,
            "y": 215,
            "page": 0
        },
        {
            "id": 33,
            "index": 341,
            "char": "!",
            "width": 10,
            "height": 41,
            "xoffset": 14,
            "yoffset": 18,
            "xadvance": 39,
            "chnl": 15,
            "x": 234,
            "y": 0,
            "page": 0
        },
        {
            "id": 49,
            "index": 317,
            "char": "1",
            "width": 32,
            "height": 41,
            "xoffset": 5,
            "yoffset": 18,
            "xadvance": 39,
            "chnl": 15,
            "x": 97,
            "y": 143,
            "page": 0
        },
        {
            "id": 50,
            "index": 318,
            "char": "2",
            "width": 26,
            "height": 41,
            "xoffset": 6,
            "yoffset": 18,
            "xadvance": 39,
            "chnl": 15,
            "x": 171,
            "y": 133,
            "page": 0
        },
        {
            "id": 52,
            "index": 320,
            "char": "4",
            "width": 30,
            "height": 41,
            "xoffset": 4,
            "yoffset": 18,
            "xadvance": 39,
            "chnl": 15,
            "x": 198,
            "y": 172,
            "page": 0
        },
        {
            "id": 55,
            "index": 323,
            "char": "7",
            "width": 26,
            "height": 41,
            "xoffset": 7,
            "yoffset": 18,
            "xadvance": 39,
            "chnl": 15,
            "x": 86,
            "y": 214,
            "page": 0
        },
        {
            "id": 63,
            "index": 345,
            "char": "?",
            "width": 23,
            "height": 41,
            "xoffset": 7,
            "yoffset": 18,
            "xadvance": 39,
            "chnl": 15,
            "x": 113,
            "y": 214,
            "page": 0
        },
        {
            "id": 65,
            "index": 4,
            "char": "A",
            "width": 41,
            "height": 41,
            "xoffset": -1,
            "yoffset": 18,
            "xadvance": 39,
            "chnl": 15,
            "x": 137,
            "y": 214,
            "page": 0
        },
        {
            "id": 66,
            "index": 15,
            "char": "B",
            "width": 33,
            "height": 41,
            "xoffset": 4,
            "yoffset": 18,
            "xadvance": 39,
            "chnl": 15,
            "x": 179,
            "y": 214,
            "page": 0
        },
        {
            "id": 68,
            "index": 22,
            "char": "D",
            "width": 35,
            "height": 41,
            "xoffset": 1,
            "yoffset": 18,
            "xadvance": 39,
            "chnl": 15,
            "x": 213,
            "y": 214,
            "page": 0
        },
        {
            "id": 69,
            "index": 26,
            "char": "E",
            "width": 36,
            "height": 41,
            "xoffset": 1,
            "yoffset": 18,
            "xadvance": 39,
            "chnl": 15,
            "x": 245,
            "y": 0,
            "page": 0
        },
        {
            "id": 70,
            "index": 36,
            "char": "F",
            "width": 36,
            "height": 41,
            "xoffset": 1,
            "yoffset": 18,
            "xadvance": 39,
            "chnl": 15,
            "x": 229,
            "y": 172,
            "page": 0
        },
        {
            "id": 72,
            "index": 42,
            "char": "H",
            "width": 37,
            "height": 41,
            "xoffset": 1,
            "yoffset": 18,
            "xadvance": 39,
            "chnl": 15,
            "x": 249,
            "y": 214,
            "page": 0
        },
        {
            "id": 73,
            "index": 45,
            "char": "I",
            "width": 29,
            "height": 41,
            "xoffset": 6,
            "yoffset": 18,
            "xadvance": 39,
            "chnl": 15,
            "x": 235,
            "y": 85,
            "page": 0
        },
        {
            "id": 74,
            "index": 56,
            "char": "J",
            "width": 33,
            "height": 41,
            "xoffset": 2,
            "yoffset": 18,
            "xadvance": 39,
            "chnl": 15,
            "x": 255,
            "y": 42,
            "page": 0
        },
        {
            "id": 76,
            "index": 60,
            "char": "L",
            "width": 37,
            "height": 41,
            "xoffset": 0,
            "yoffset": 18,
            "xadvance": 39,
            "chnl": 15,
            "x": 282,
            "y": 0,
            "page": 0
        },
        {
            "id": 78,
            "index": 67,
            "char": "N",
            "width": 38,
            "height": 41,
            "xoffset": 1,
            "yoffset": 18,
            "xadvance": 39,
            "chnl": 15,
            "x": 240,
            "y": 127,
            "page": 0
        },
        {
            "id": 80,
            "index": 84,
            "char": "P",
            "width": 34,
            "height": 41,
            "xoffset": 2,
            "yoffset": 18,
            "xadvance": 39,
            "chnl": 15,
            "x": 265,
            "y": 84,
            "page": 0
        },
        {
            "id": 82,
            "index": 87,
            "char": "R",
            "width": 36,
            "height": 41,
            "xoffset": 3,
            "yoffset": 18,
            "xadvance": 39,
            "chnl": 15,
            "x": 289,
            "y": 42,
            "page": 0
        },
        {
            "id": 84,
            "index": 97,
            "char": "T",
            "width": 35,
            "height": 41,
            "xoffset": 2,
            "yoffset": 18,
            "xadvance": 39,
            "chnl": 15,
            "x": 320,
            "y": 0,
            "page": 0
        },
        {
            "id": 85,
            "index": 100,
            "char": "U",
            "width": 41,
            "height": 41,
            "xoffset": 0,
            "yoffset": 18,
            "xadvance": 39,
            "chnl": 15,
            "x": 266,
            "y": 169,
            "page": 0
        },
        {
            "id": 87,
            "index": 112,
            "char": "W",
            "width": 40,
            "height": 41,
            "xoffset": 0,
            "yoffset": 18,
            "xadvance": 39,
            "chnl": 15,
            "x": 279,
            "y": 126,
            "page": 0
        },
        {
            "id": 88,
            "index": 117,
            "char": "X",
            "width": 36,
            "height": 41,
            "xoffset": 1,
            "yoffset": 18,
            "xadvance": 39,
            "chnl": 15,
            "x": 300,
            "y": 84,
            "page": 0
        },
        {
            "id": 89,
            "index": 118,
            "char": "Y",
            "width": 35,
            "height": 41,
            "xoffset": 2,
            "yoffset": 18,
            "xadvance": 39,
            "chnl": 15,
            "x": 326,
            "y": 42,
            "page": 0
        },
        {
            "id": 90,
            "index": 123,
            "char": "Z",
            "width": 30,
            "height": 41,
            "xoffset": 5,
            "yoffset": 18,
            "xadvance": 39,
            "chnl": 15,
            "x": 356,
            "y": 0,
            "page": 0
        },
        {
            "id": 98,
            "index": 167,
            "char": "b",
            "width": 34,
            "height": 41,
            "xoffset": 1,
            "yoffset": 18,
            "xadvance": 39,
            "chnl": 15,
            "x": 287,
            "y": 211,
            "page": 0
        },
        {
            "id": 100,
            "index": 174,
            "char": "d",
            "width": 34,
            "height": 41,
            "xoffset": 4,
            "yoffset": 18,
            "xadvance": 39,
            "chnl": 15,
            "x": 308,
            "y": 168,
            "page": 0
        },
        {
            "id": 102,
            "index": 188,
            "char": "f",
            "width": 28,
            "height": 41,
            "xoffset": 7,
            "yoffset": 18,
            "xadvance": 39,
            "chnl": 15,
            "x": 320,
            "y": 126,
            "page": 0
        },
        {
            "id": 104,
            "index": 194,
            "char": "h",
            "width": 36,
            "height": 41,
            "xoffset": 2,
            "yoffset": 18,
            "xadvance": 39,
            "chnl": 15,
            "x": 337,
            "y": 84,
            "page": 0
        },
        {
            "id": 105,
            "index": 197,
            "char": "i",
            "width": 32,
            "height": 41,
            "xoffset": 6,
            "yoffset": 18,
            "xadvance": 39,
            "chnl": 15,
            "x": 362,
            "y": 42,
            "page": 0
        },
        {
            "id": 107,
            "index": 211,
            "char": "k",
            "width": 35,
            "height": 41,
            "xoffset": 3,
            "yoffset": 18,
            "xadvance": 39,
            "chnl": 15,
            "x": 387,
            "y": 0,
            "page": 0
        },
        {
            "id": 108,
            "index": 214,
            "char": "l",
            "width": 32,
            "height": 41,
            "xoffset": 5,
            "yoffset": 18,
            "xadvance": 39,
            "chnl": 15,
            "x": 322,
            "y": 210,
            "page": 0
        },
        {
            "id": 109,
            "index": 220,
            "char": "m",
            "width": 41,
            "height": 29,
            "xoffset": -1,
            "yoffset": 30,
            "xadvance": 39,
            "chnl": 15,
            "x": 130,
            "y": 184,
            "page": 0
        },
        {
            "id": 112,
            "index": 239,
            "char": "p",
            "width": 33,
            "height": 41,
            "xoffset": 2,
            "yoffset": 30,
            "xadvance": 39,
            "chnl": 15,
            "x": 343,
            "y": 168,
            "page": 0
        },
        {
            "id": 113,
            "index": 241,
            "char": "q",
            "width": 32,
            "height": 41,
            "xoffset": 4,
            "yoffset": 30,
            "xadvance": 39,
            "chnl": 15,
            "x": 349,
            "y": 126,
            "page": 0
        },
        {
            "id": 121,
            "index": 299,
            "char": "y",
            "width": 34,
            "height": 39,
            "xoffset": 3,
            "yoffset": 31,
            "xadvance": 39,
            "chnl": 15,
            "x": 374,
            "y": 84,
            "page": 0
        },
        {
            "id": 116,
            "index": 253,
            "char": "t",
            "width": 28,
            "height": 38,
            "xoffset": 5,
            "yoffset": 22,
            "xadvance": 39,
            "chnl": 15,
            "x": 395,
            "y": 42,
            "page": 0
        },
        {
            "id": 117,
            "index": 256,
            "char": "u",
            "width": 37,
            "height": 30,
            "xoffset": 1,
            "yoffset": 30,
            "xadvance": 39,
            "chnl": 15,
            "x": 423,
            "y": 0,
            "page": 0
        },
        {
            "id": 110,
            "index": 221,
            "char": "n",
            "width": 36,
            "height": 29,
            "xoffset": 2,
            "yoffset": 30,
            "xadvance": 39,
            "chnl": 15,
            "x": 461,
            "y": 0,
            "page": 0
        },
        {
            "id": 59,
            "index": 349,
            "char": ";",
            "width": 11,
            "height": 35,
            "xoffset": 15,
            "yoffset": 30,
            "xadvance": 39,
            "chnl": 15,
            "x": 58,
            "y": 52,
            "page": 0
        },
        {
            "id": 118,
            "index": 292,
            "char": "v",
            "width": 35,
            "height": 29,
            "xoffset": 2,
            "yoffset": 31,
            "xadvance": 39,
            "chnl": 15,
            "x": 461,
            "y": 30,
            "page": 0
        },
        {
            "id": 60,
            "index": 387,
            "char": "<",
            "width": 34,
            "height": 30,
            "xoffset": 0,
            "yoffset": 25,
            "xadvance": 39,
            "chnl": 15,
            "x": 424,
            "y": 31,
            "page": 0
        },
        {
            "id": 62,
            "index": 386,
            "char": ">",
            "width": 34,
            "height": 30,
            "xoffset": 4,
            "yoffset": 25,
            "xadvance": 39,
            "chnl": 15,
            "x": 355,
            "y": 210,
            "page": 0
        },
        {
            "id": 120,
            "index": 298,
            "char": "x",
            "width": 33,
            "height": 28,
            "xoffset": 3,
            "yoffset": 31,
            "xadvance": 39,
            "chnl": 15,
            "x": 74,
            "y": 185,
            "page": 0
        },
        {
            "id": 95,
            "index": 351,
            "char": "_",
            "width": 31,
            "height": 7,
            "xoffset": 4,
            "yoffset": 52,
            "xadvance": 39,
            "chnl": 15,
            "x": 43,
            "y": 245,
            "page": 0
        },
        {
            "id": 97,
            "index": 156,
            "char": "a",
            "width": 31,
            "height": 30,
            "xoffset": 6,
            "yoffset": 30,
            "xadvance": 39,
            "chnl": 15,
            "x": 377,
            "y": 168,
            "page": 0
        },
        {
            "id": 111,
            "index": 228,
            "char": "o",
            "width": 31,
            "height": 30,
            "xoffset": 4,
            "yoffset": 30,
            "xadvance": 39,
            "chnl": 15,
            "x": 382,
            "y": 124,
            "page": 0
        },
        {
            "id": 58,
            "index": 338,
            "char": ":",
            "width": 11,
            "height": 30,
            "xoffset": 15,
            "yoffset": 30,
            "xadvance": 39,
            "chnl": 15,
            "x": 498,
            "y": 0,
            "page": 0
        },
        {
            "id": 99,
            "index": 168,
            "char": "c",
            "width": 29,
            "height": 30,
            "xoffset": 4,
            "yoffset": 30,
            "xadvance": 39,
            "chnl": 15,
            "x": 409,
            "y": 81,
            "page": 0
        },
        {
            "id": 101,
            "index": 178,
            "char": "e",
            "width": 29,
            "height": 30,
            "xoffset": 5,
            "yoffset": 30,
            "xadvance": 39,
            "chnl": 15,
            "x": 459,
            "y": 60,
            "page": 0
        },
        {
            "id": 115,
            "index": 246,
            "char": "s",
            "width": 26,
            "height": 30,
            "xoffset": 6,
            "yoffset": 30,
            "xadvance": 39,
            "chnl": 15,
            "x": 390,
            "y": 199,
            "page": 0
        },
        {
            "id": 114,
            "index": 242,
            "char": "r",
            "width": 29,
            "height": 29,
            "xoffset": 5,
            "yoffset": 30,
            "xadvance": 39,
            "chnl": 15,
            "x": 409,
            "y": 155,
            "page": 0
        },
        {
            "id": 122,
            "index": 304,
            "char": "z",
            "width": 27,
            "height": 28,
            "xoffset": 7,
            "yoffset": 31,
            "xadvance": 39,
            "chnl": 15,
            "x": 414,
            "y": 112,
            "page": 0
        },
        {
            "id": 42,
            "index": 334,
            "char": "*",
            "width": 27,
            "height": 24,
            "xoffset": 7,
            "yoffset": 20,
            "xadvance": 39,
            "chnl": 15,
            "x": 0,
            "y": 145,
            "page": 0
        },
        {
            "id": 43,
            "index": 380,
            "char": "+",
            "width": 26,
            "height": 26,
            "xoffset": 7,
            "yoffset": 28,
            "xadvance": 39,
            "chnl": 15,
            "x": 390,
            "y": 230,
            "page": 0
        },
        {
            "id": 126,
            "index": 392,
            "char": "~",
            "width": 26,
            "height": 12,
            "xoffset": 9,
            "yoffset": 26,
            "xadvance": 39,
            "chnl": 15,
            "x": 382,
            "y": 155,
            "page": 0
        },
        {
            "id": 61,
            "index": 384,
            "char": "=",
            "width": 24,
            "height": 18,
            "xoffset": 7,
            "yoffset": 33,
            "xadvance": 39,
            "chnl": 15,
            "x": 424,
            "y": 62,
            "page": 0
        },
        {
            "id": 94,
            "index": 415,
            "char": "^",
            "width": 23,
            "height": 24,
            "xoffset": 8,
            "yoffset": 23,
            "xadvance": 39,
            "chnl": 15,
            "x": 489,
            "y": 60,
            "page": 0
        },
        {
            "id": 45,
            "index": 360,
            "char": "-",
            "width": 23,
            "height": 7,
            "xoffset": 8,
            "yoffset": 39,
            "xadvance": 39,
            "chnl": 15,
            "x": 489,
            "y": 85,
            "page": 0
        },
        {
            "id": 34,
            "index": 347,
            "char": "\"",
            "width": 14,
            "height": 19,
            "xoffset": 12,
            "yoffset": 18,
            "xadvance": 39,
            "chnl": 15,
            "x": 497,
            "y": 31,
            "page": 0
        },
        {
            "id": 39,
            "index": 348,
            "char": "'",
            "width": 8,
            "height": 19,
            "xoffset": 16,
            "yoffset": 18,
            "xadvance": 39,
            "chnl": 15,
            "x": 97,
            "y": 101,
            "page": 0
        },
        {
            "id": 96,
            "index": 427,
            "char": "`",
            "width": 17,
            "height": 13,
            "xoffset": -2,
            "yoffset": 15,
            "xadvance": 39,
            "chnl": 15,
            "x": 40,
            "y": 102,
            "page": 0
        },
        {
            "id": 44,
            "index": 339,
            "char": ",",
            "width": 11,
            "height": 16,
            "xoffset": 14,
            "yoffset": 49,
            "xadvance": 39,
            "chnl": 15,
            "x": 439,
            "y": 93,
            "page": 0
        },
        {
            "id": 46,
            "index": 344,
            "char": ".",
            "width": 11,
            "height": 11,
            "xoffset": 14,
            "yoffset": 49,
            "xadvance": 39,
            "chnl": 15,
            "x": 58,
            "y": 88,
            "page": 0
        },
        {
            "id": 32,
            "index": 3,
            "char": " ",
            "width": 0,
            "height": 0,
            "xoffset": -2,
            "yoffset": 55,
            "xadvance": 39,
            "chnl": 15,
            "x": 153,
            "y": 48,
            "page": 0
        }
    ],
    "info": {
        "face": "CutiveMono-Regular",
        "size": 64,
        "bold": 0,
        "italic": 0,
        "charset": [
            " ",
            "!",
            "\"",
            "#",
            "$",
            "%",
            "&",
            "'",
            "(",
            ")",
            "*",
            "+",
            ",",
            "-",
            ".",
            "/",
            "0",
            "1",
            "2",
            "3",
            "4",
            "5",
            "6",
            "7",
            "8",
            "9",
            ":",
            ";",
            "<",
            "=",
            ">",
            "?",
            "@",
            "A",
            "B",
            "C",
            "D",
            "E",
            "F",
            "G",
            "H",
            "I",
            "J",
            "K",
            "L",
            "M",
            "N",
            "O",
            "P",
            "Q",
            "R",
            "S",
            "T",
            "U",
            "V",
            "W",
            "X",
            "Y",
            "Z",
            "[",
            "\\",
            "]",
            "^",
            "_",
            "`",
            "a",
            "b",
            "c",
            "d",
            "e",
            "f",
            "g",
            "h",
            "i",
            "j",
            "k",
            "l",
            "m",
            "n",
            "o",
            "p",
            "q",
            "r",
            "s",
            "t",
            "u",
            "v",
            "w",
            "x",
            "y",
            "z",
            "{",
            "|",
            "}",
            "~"
        ],
        "unicode": 1,
        "stretchH": 100,
        "smooth": 1,
        "aa": 1,
        "padding": [
            2,
            2,
            2,
            2
        ],
        "spacing": [
            0,
            0
        ],
        "outline": 0
    },
    "common": {
        "lineHeight": 70,
        "base": 55,
        "scaleW": 512,
        "scaleH": 256,
        "pages": 1,
        "packed": 0,
        "alphaChnl": 0,
        "redChnl": 0,
        "greenChnl": 0,
        "blueChnl": 0
    },
    "distanceField": {
        "fieldType": "msdf",
        "distanceRange": 4
    },
    "kernings": []
}